<?xml version="1.0" encoding="UTF-8"?>
<ns2:test-suite xmlns:ns2="urn:model.allure.qatools.yandex.ru" start="1499085855836" stop="1499085878436">
	<name>File Upload 1</name>
	<title>File Upload 1</title>
	<test-cases>
		<test-case start="1499085855836" stop="1499085878436" status="passed">
			<name>first file upload</name>
			<title>first file upload</title>
			<description></description>
			<labels>
			</labels>
			<parameters>
			</parameters>
			<steps>
			</steps>
			<attachments>
				<attachment title="Screenshot" source="3c6ade7c-752c-467a-8ac3-4b2b0d11055c-attachment.png" type="image/png" size="289681"/>
			</attachments>
		</test-case>
	</test-cases>
</ns2:test-suite>