<?xml version="1.0" encoding="UTF-8"?>
<ns2:test-suite xmlns:ns2="urn:model.allure.qatools.yandex.ru" start="1499359289316" stop="1499359293694">
	<name>Add Staff Heading</name>
	<title>Add Staff Heading</title>
	<test-cases>
		<test-case start="1499359289316" stop="1499359293693" status="passed">
			<name>should verify the Add Staff heading text</name>
			<title>should verify the Add Staff heading text</title>
			<description></description>
			<labels>
			</labels>
			<parameters>
			</parameters>
			<steps>
			</steps>
			<attachments>
				<attachment title="Screenshot" source="abc9f477-bc6b-4253-9957-a65427d02e28-attachment.png" type="image/png" size="48762"/>
			</attachments>
		</test-case>
	</test-cases>
</ns2:test-suite>