<?xml version="1.0" encoding="UTF-8"?>
<ns2:test-suite xmlns:ns2="urn:model.allure.qatools.yandex.ru" start="1496574220324" stop="1496574222721">
	<name>Header Bar</name>
	<title>Header Bar</title>
	<test-cases>
		<test-case start="1496574220324" stop="1496574222719" status="passed">
			<name>should highlight the header bar</name>
			<title>should highlight the header bar</title>
			<description></description>
			<labels>
			</labels>
			<parameters>
			</parameters>
			<steps>
			</steps>
			<attachments>
				<attachment title="Screenshot" source="e6b3b464-3434-4ccc-93fc-efa323f759cd-attachment.png" type="image/png" size="92192"/>
			</attachments>
		</test-case>
	</test-cases>
</ns2:test-suite>