<?xml version="1.0" encoding="UTF-8"?>
<ns2:test-suite xmlns:ns2="urn:model.allure.qatools.yandex.ru" start="1497858984515" stop="1497858985146">
	<name>Profile Smoke Tests</name>
	<title>Profile Smoke Tests</title>
	<test-cases>
		<test-case start="1497858984515" stop="1497858984838" status="passed">
			<name>checks the page url</name>
			<title>checks the page url</title>
			<description></description>
			<labels>
			</labels>
			<parameters>
			</parameters>
			<steps>
			</steps>
			<attachments>
				<attachment title="Screenshot" source="96877987-3772-40b8-bfad-63d4cee787c1-attachment.png" type="image/png" size="82794"/>
			</attachments>
		</test-case>
		<test-case start="1497858984838" stop="1497858985145" status="passed">
			<name>checks the Image loaded</name>
			<title>checks the Image loaded</title>
			<description></description>
			<labels>
			</labels>
			<parameters>
			</parameters>
			<steps>
			</steps>
			<attachments>
				<attachment title="Screenshot" source="acf0079d-b431-4189-a7c9-7094e72d4ace-attachment.png" type="image/png" size="82761"/>
			</attachments>
		</test-case>
	</test-cases>
</ns2:test-suite>