<?xml version="1.0" encoding="UTF-8"?>
<ns2:test-suite xmlns:ns2="urn:model.allure.qatools.yandex.ru" start="1496937249916" stop="1496937254454">
	<name>Clinic Phone</name>
	<title>Clinic Phone</title>
	<test-cases>
		<test-case start="1496937249916" stop="1496937254453" status="passed">
			<name>set clinic phone number</name>
			<title>set clinic phone number</title>
			<description></description>
			<labels>
			</labels>
			<parameters>
			</parameters>
			<steps>
			</steps>
			<attachments>
				<attachment title="Screenshot" source="e35b0e0e-4fd0-44e7-ab00-093ad1decf54-attachment.png" type="image/png" size="36588"/>
			</attachments>
		</test-case>
	</test-cases>
</ns2:test-suite>