<?xml version="1.0" encoding="UTF-8"?>
<ns2:test-suite xmlns:ns2="urn:model.allure.qatools.yandex.ru" start="1501483289839" stop="1501483293353">
	<name>Setting the email</name>
	<title>Setting the email</title>
	<test-cases>
		<test-case start="1501483289839" stop="1501483293353" status="passed">
			<name>should set the email</name>
			<title>should set the email</title>
			<description></description>
			<labels>
			</labels>
			<parameters>
			</parameters>
			<steps>
			</steps>
			<attachments>
				<attachment title="Screenshot" source="eac1e8de-d0ae-43d4-a3fc-e6603ba21293-attachment.png" type="image/png" size="76444"/>
			</attachments>
		</test-case>
	</test-cases>
</ns2:test-suite>