<?xml version="1.0" encoding="UTF-8"?>
<ns2:test-suite xmlns:ns2="urn:model.allure.qatools.yandex.ru" start="1499087374474" stop="1499087397080">
	<name>File Upload 1</name>
	<title>File Upload 1</title>
	<test-cases>
		<test-case start="1499087374474" stop="1499087397080" status="passed">
			<name>first file upload</name>
			<title>first file upload</title>
			<description></description>
			<labels>
			</labels>
			<parameters>
			</parameters>
			<steps>
			</steps>
			<attachments>
				<attachment title="Screenshot" source="4bcf20e2-1a09-4b1a-a2ce-b9fd31782e91-attachment.png" type="image/png" size="289641"/>
			</attachments>
		</test-case>
	</test-cases>
</ns2:test-suite>