<?xml version="1.0" encoding="UTF-8"?>
<ns2:test-suite xmlns:ns2="urn:model.allure.qatools.yandex.ru" start="1496839757412" stop="1496839762151">
	<name>Set Doctors</name>
	<title>Set Doctors</title>
	<test-cases>
		<test-case start="1496839757412" stop="1496839762151" status="passed">
			<name>should select whether owner is a doctor or not and then add doctors based on that</name>
			<title>should select whether owner is a doctor or not and then add doctors based on that</title>
			<description></description>
			<labels>
			</labels>
			<parameters>
			</parameters>
			<steps>
			</steps>
			<attachments>
				<attachment title="Screenshot" source="b99a2315-8beb-4cba-8fc6-470dc6bb8f60-attachment.png" type="image/png" size="48566"/>
			</attachments>
		</test-case>
	</test-cases>
</ns2:test-suite>