{
  "uid" : "2e57080c11c58d1b",
  "name" : "enter the specialisation",
  "title" : "enter the specialisation",
  "time" : {
    "start" : 1497329187097,
    "stop" : 1497329194145,
    "duration" : 7048
  },
  "summary" : {
    "attachments" : 1,
    "steps" : 0
  },
  "failure" : null,
  "description" : {
    "value" : "",
    "type" : "TEXT"
  },
  "severity" : "NORMAL",
  "status" : "PASSED",
  "testId" : null,
  "suite" : {
    "uid" : "5c075f0dade7036a",
    "name" : "Specialisation",
    "title" : "Specialisation"
  },
  "steps" : [ ],
  "attachments" : [ {
    "title" : "Screenshot",
    "source" : "7bfb1d0a-793e-4194-b34e-49dff43c870c-attachment.png",
    "type" : "image/png",
    "size" : 36933,
    "uid" : "3e6867c7426b770e"
  } ],
  "issues" : [ ],
  "labels" : [ {
    "name" : "suite-name",
    "value" : "Specialisation"
  }, {
    "name" : "suite-title",
    "value" : "Specialisation"
  } ],
  "parameters" : [ ]
}