{
  "uid" : "3964ec137aa72b42",
  "name" : "will verify the URL of verification page",
  "title" : "will verify the URL of verification page",
  "time" : {
    "start" : 1497330027318,
    "stop" : 1497330028619,
    "duration" : 1301
  },
  "summary" : {
    "attachments" : 1,
    "steps" : 0
  },
  "failure" : null,
  "description" : {
    "value" : "",
    "type" : "TEXT"
  },
  "severity" : "NORMAL",
  "status" : "PASSED",
  "testId" : null,
  "suite" : {
    "uid" : "dbc86bd2139b44eb",
    "name" : "Verification URL",
    "title" : "Verification URL"
  },
  "steps" : [ ],
  "attachments" : [ {
    "title" : "Screenshot",
    "source" : "81a4ab86-dd5d-44e0-8eee-988d6d36c0a4-attachment.png",
    "type" : "image/png",
    "size" : 55432,
    "uid" : "fe941050d4743415"
  } ],
  "issues" : [ ],
  "labels" : [ {
    "name" : "suite-name",
    "value" : "Verification URL"
  }, {
    "name" : "suite-title",
    "value" : "Verification URL"
  } ],
  "parameters" : [ ]
}