{
  "uid" : "40484d72909d030c",
  "name" : "Privacy section is displayed",
  "title" : "Privacy section is displayed",
  "time" : {
    "start" : 1497329866044,
    "stop" : 1497329868438,
    "duration" : 2394
  },
  "summary" : {
    "attachments" : 1,
    "steps" : 0
  },
  "failure" : null,
  "description" : {
    "value" : "",
    "type" : "TEXT"
  },
  "severity" : "NORMAL",
  "status" : "PASSED",
  "testId" : null,
  "suite" : {
    "uid" : "5c40d6aeb18fe383",
    "name" : "Privacy Section",
    "title" : "Privacy Section"
  },
  "steps" : [ ],
  "attachments" : [ {
    "title" : "Screenshot",
    "source" : "58c6acb0-e9c9-487a-8b50-16e5639b191d-attachment.png",
    "type" : "image/png",
    "size" : 80781,
    "uid" : "3f516cd7f95fd416"
  } ],
  "issues" : [ ],
  "labels" : [ {
    "name" : "suite-name",
    "value" : "Privacy Section"
  }, {
    "name" : "suite-title",
    "value" : "Privacy Section"
  } ],
  "parameters" : [ ]
}