{
  "uid" : "6c1ff62b831735c7",
  "name" : "checks if content header is displayed",
  "title" : "checks if content header is displayed",
  "time" : {
    "start" : 1497338623938,
    "stop" : 1497338626332,
    "duration" : 2394
  },
  "summary" : {
    "attachments" : 1,
    "steps" : 0
  },
  "failure" : null,
  "description" : {
    "value" : "",
    "type" : "TEXT"
  },
  "severity" : "NORMAL",
  "status" : "PASSED",
  "testId" : null,
  "suite" : {
    "uid" : "4ef17d51073ba35a",
    "name" : "Content Heading",
    "title" : "Content Heading"
  },
  "steps" : [ ],
  "attachments" : [ {
    "title" : "Screenshot",
    "source" : "18ecb82e-4dad-459a-954e-9979f43e91be-attachment.png",
    "type" : "image/png",
    "size" : 82188,
    "uid" : "2db28006f17a967d"
  } ],
  "issues" : [ ],
  "labels" : [ {
    "name" : "suite-name",
    "value" : "Content Heading"
  }, {
    "name" : "suite-title",
    "value" : "Content Heading"
  } ],
  "parameters" : [ ]
}