{
  "uid" : "70503a80441836f0",
  "name" : "opening a new window and get OTP",
  "title" : "opening a new window and get OTP",
  "time" : {
    "start" : 1497350004726,
    "stop" : 1497350023301,
    "duration" : 18575
  },
  "summary" : {
    "attachments" : 1,
    "steps" : 0
  },
  "failure" : null,
  "description" : {
    "value" : "",
    "type" : "TEXT"
  },
  "severity" : "NORMAL",
  "status" : "PASSED",
  "testId" : null,
  "suite" : {
    "uid" : "d8a87a69d3699fe6",
    "name" : "Go to Mahaflox",
    "title" : "Go to Mahaflox"
  },
  "steps" : [ ],
  "attachments" : [ {
    "title" : "Screenshot",
    "source" : "6bd52898-7935-4c7f-a952-917990966bea-attachment.png",
    "type" : "image/png",
    "size" : 73876,
    "uid" : "6b0d04ec690aefc8"
  } ],
  "issues" : [ ],
  "labels" : [ {
    "name" : "suite-name",
    "value" : "Go to Mahaflox"
  }, {
    "name" : "suite-title",
    "value" : "Go to Mahaflox"
  } ],
  "parameters" : [ ]
}