{
  "uid" : "83c246f730936614",
  "name" : "checks if the content header part 2 is displayed",
  "title" : "checks if the content header part 2 is displayed",
  "time" : {
    "start" : 1497349971793,
    "stop" : 1497349974206,
    "duration" : 2413
  },
  "summary" : {
    "attachments" : 1,
    "steps" : 0
  },
  "failure" : null,
  "description" : {
    "value" : "",
    "type" : "TEXT"
  },
  "severity" : "NORMAL",
  "status" : "PASSED",
  "testId" : null,
  "suite" : {
    "uid" : "4ef17d51073ba35a",
    "name" : "Content Heading",
    "title" : "Content Heading"
  },
  "steps" : [ ],
  "attachments" : [ {
    "title" : "Screenshot",
    "source" : "556401ee-9d46-47d1-b941-5b898f34c4b3-attachment.png",
    "type" : "image/png",
    "size" : 80984,
    "uid" : "447d1589772ce27a"
  } ],
  "issues" : [ ],
  "labels" : [ {
    "name" : "suite-name",
    "value" : "Content Heading"
  }, {
    "name" : "suite-title",
    "value" : "Content Heading"
  } ],
  "parameters" : [ ]
}