{
  "uid" : "99ed69180c8aa5ed",
  "name" : "opening a new window",
  "title" : "opening a new window",
  "time" : {
    "start" : 1495037434214,
    "stop" : 1495037448061,
    "duration" : 13847
  },
  "summary" : {
    "attachments" : 1,
    "steps" : 0
  },
  "failure" : null,
  "description" : {
    "value" : "",
    "type" : "TEXT"
  },
  "severity" : "NORMAL",
  "status" : "PASSED",
  "testId" : null,
  "suite" : {
    "uid" : "76e11292be67af1c",
    "name" : "Open a new window",
    "title" : "Open a new window"
  },
  "steps" : [ ],
  "attachments" : [ {
    "title" : "Screenshot",
    "source" : "70c030b3-eb0b-4131-9462-5a41a4b5a16d-attachment.png",
    "type" : "image/png",
    "size" : 90201,
    "uid" : "779d293bc9ed0c1e"
  } ],
  "issues" : [ ],
  "labels" : [ {
    "name" : "suite-name",
    "value" : "Open a new window"
  }, {
    "name" : "suite-title",
    "value" : "Open a new window"
  } ],
  "parameters" : [ ]
}