{
  "uid" : "a011227461d84107",
  "name" : "should select whether owner is a doctor or not and then add doctors based on that",
  "title" : "should select whether owner is a doctor or not and then add doctors based on that",
  "time" : {
    "start" : 1497358333228,
    "stop" : 1497358337993,
    "duration" : 4765
  },
  "summary" : {
    "attachments" : 1,
    "steps" : 0
  },
  "failure" : null,
  "description" : {
    "value" : "",
    "type" : "TEXT"
  },
  "severity" : "NORMAL",
  "status" : "PASSED",
  "testId" : null,
  "suite" : {
    "uid" : "36d4b5c442c34fe5",
    "name" : "Set Doctors",
    "title" : "Set Doctors"
  },
  "steps" : [ ],
  "attachments" : [ {
    "title" : "Screenshot",
    "source" : "00dddcdb-9252-4814-a360-12e7fccb06c9-attachment.png",
    "type" : "image/png",
    "size" : 48449,
    "uid" : "33d17e3666774a3d"
  } ],
  "issues" : [ ],
  "labels" : [ {
    "name" : "suite-name",
    "value" : "Set Doctors"
  }, {
    "name" : "suite-title",
    "value" : "Set Doctors"
  } ],
  "parameters" : [ ]
}