{
  "uid" : "b2cc2959bc616f89",
  "name" : "uploads third document",
  "title" : "uploads third document",
  "time" : {
    "start" : 1497380448669,
    "stop" : 1497380471149,
    "duration" : 22480
  },
  "summary" : {
    "attachments" : 1,
    "steps" : 0
  },
  "failure" : null,
  "description" : {
    "value" : "",
    "type" : "TEXT"
  },
  "severity" : "NORMAL",
  "status" : "PASSED",
  "testId" : null,
  "suite" : {
    "uid" : "82b7e5137819d2a1",
    "name" : "File Upload 3",
    "title" : "File Upload 3"
  },
  "steps" : [ ],
  "attachments" : [ {
    "title" : "Screenshot",
    "source" : "8baed56b-3507-4359-806d-dd945fc85ac6-attachment.png",
    "type" : "image/png",
    "size" : 57627,
    "uid" : "d8a68047f0997784"
  } ],
  "issues" : [ ],
  "labels" : [ {
    "name" : "suite-name",
    "value" : "File Upload 3"
  }, {
    "name" : "suite-title",
    "value" : "File Upload 3"
  } ],
  "parameters" : [ ]
}