{
  "uid" : "c38c132d3285ffea",
  "name" : "setting short password",
  "title" : "setting short password",
  "time" : {
    "start" : 1495696689801,
    "stop" : 1495696693138,
    "duration" : 3337
  },
  "summary" : {
    "attachments" : 1,
    "steps" : 0
  },
  "failure" : null,
  "description" : {
    "value" : "",
    "type" : "TEXT"
  },
  "severity" : "NORMAL",
  "status" : "PASSED",
  "testId" : null,
  "suite" : {
    "uid" : "fb10d75b89306d89",
    "name" : "Short Password",
    "title" : "Short Password"
  },
  "steps" : [ ],
  "attachments" : [ {
    "title" : "Screenshot",
    "source" : "d3f73236-0f88-415d-bab4-36bd75a12d2d-attachment.png",
    "type" : "image/png",
    "size" : 95769,
    "uid" : "8a2ff40457acf143"
  } ],
  "issues" : [ ],
  "labels" : [ {
    "name" : "suite-name",
    "value" : "Short Password"
  }, {
    "name" : "suite-title",
    "value" : "Short Password"
  } ],
  "parameters" : [ ]
}