{
  "uid" : "ca2249af35b59108",
  "name" : "Entering the OTP",
  "title" : "Entering the OTP",
  "time" : {
    "start" : 1500450226287,
    "stop" : 1500450233773,
    "duration" : 7486
  },
  "summary" : {
    "attachments" : 1,
    "steps" : 0
  },
  "failure" : null,
  "description" : {
    "value" : "",
    "type" : "TEXT"
  },
  "severity" : "NORMAL",
  "status" : "PASSED",
  "testId" : null,
  "suite" : {
    "uid" : "818816e70851f409",
    "name" : "OTP",
    "title" : "OTP"
  },
  "steps" : [ ],
  "attachments" : [ {
    "title" : "Screenshot",
    "source" : "9100e2e7-85e7-43c4-bcbc-1174e56066e3-attachment.png",
    "type" : "image/png",
    "size" : 68361,
    "uid" : "d9c7f9dc1e233b83"
  } ],
  "issues" : [ ],
  "labels" : [ {
    "name" : "suite-name",
    "value" : "OTP"
  }, {
    "name" : "suite-title",
    "value" : "OTP"
  } ],
  "parameters" : [ ]
}